{"data_mtime":1736829011,"dep_lines":[8,24,25,75,6,7,12,21,23,71,3,4,71,1,1,1,1,1,1,1,1,1,1],"dep_prios":[5,20,20,20,5,5,25,20,20,20,5,5,20,5,20,20,20,20,20,30,30,30,30],"dependencies":["torch._dynamo.variables.base","torch._dynamo.variables.builder","torch._dynamo.variables.torch","torch._dynamo.variables.misc","torch._dynamo.bytecode_transformation","torch._dynamo.exc","torch._dynamo.symbolic_convert","torch.backends.cuda","torch._dynamo.source","torch._C","inspect","typing","torch","builtins","operator","torch.nn","math","torch.distributed._functional_collectives","multiprocessing.reduction","abc","importlib","importlib.machinery","torch._guards"],"hash":"800ec28d5ea5de44c7f16baa654b9f3b2d03753c","id":"torch._dynamo.variables.sdpa","ignore_all":true,"interface_hash":"d3c5056aa12d7fbe1a82252867856381a10f42a8","mtime":1733802971,"options":{"allow_redefinition":false,"allow_untyped_globals":false,"always_false":[],"always_true":[],"bazel":false,"check_untyped_defs":false,"disable_bytearray_promotion":false,"disable_error_code":[],"disable_memoryview_promotion":false,"disabled_error_codes":[],"disallow_any_decorated":false,"disallow_any_explicit":false,"disallow_any_expr":false,"disallow_any_generics":false,"disallow_any_unimported":false,"disallow_incomplete_defs":false,"disallow_subclassing_any":false,"disallow_untyped_calls":false,"disallow_untyped_decorators":false,"disallow_untyped_defs":false,"enable_error_code":[],"enabled_error_codes":[],"extra_checks":false,"follow_imports":"normal","follow_imports_for_stubs":false,"ignore_errors":false,"ignore_missing_imports":false,"implicit_optional":false,"implicit_reexport":true,"local_partial_types":false,"mypyc":false,"old_type_inference":false,"platform":"linux","plugins":[],"strict_concatenate":false,"strict_equality":false,"strict_optional":true,"warn_no_return":true,"warn_return_any":false,"warn_unreachable":false,"warn_unused_ignores":false},"path":"/home/russell/dotfiles/gitthings/freqtrade/.venv/lib/python3.12/site-packages/torch/_dynamo/variables/sdpa.py","plugin_data":null,"size":3244,"suppressed":[],"version_id":"1.13.0"}